chik_rs-0.28.2.dist-info/METADATA
chik_rs-0.28.2.dist-info/WHEEL
chik_rs/__init__.py
chik_rs/chik_rs.cp312-win_amd64.pyd
chik_rs/chik_rs.pyi
chik_rs/py.typed
chik_rs/sized_byte_class.py
chik_rs/sized_bytes.py
chik_rs/sized_ints.py
chik_rs/spend.py
chik_rs/struct_stream.py
chik_rs-0.28.2.dist-info/RECORD
