Metadata-Version: 2.4
Name: chik_rs
Version: 0.28.2
Requires-Dist: typing-extensions
Home-Page: https://github.com/Chik-Network/chik_rs
